DeformHeadCT/DataPreparation.py
DeformHeadCT/DeformVolume.py
DeformHeadCT/DeformVolumeOld.py
DeformHeadCT/VolumeInfo.py
DeformHeadCT/__init__.py
DeformHeadCT/deformation.py
DeformHeadCT/utils.py
CTHeadDeformation-0.1.4.dist-info/LICENSE.md
CTHeadDeformation-0.1.4.dist-info/METADATA
CTHeadDeformation-0.1.4.dist-info/WHEEL
CTHeadDeformation-0.1.4.dist-info/top_level.txt
CTHeadDeformation-0.1.4.dist-info/RECORD
