Metadata-Version: 2.1
Name: CTHeadDeformation
Version: 0.1.4
Summary: Perform Realistic Head Deformations
Home-page: https://github.com/ACRF-Image-X-Institute/CTHeadDeformation
Download-URL: 
Author: Mark Gardner
Author-email: mark.gardner@sydney.edu.au
License: MIT
Keywords: CT,deformation,head and neck
Requires-Python: >=3.7
License-File: LICENSE.md
Requires-Dist: SimpleITK
Requires-Dist: platipy
